LICENSE
MANIFEST.in
requirements.txt
requirements_dev.txt
setup.cfg
setup.py
cedar/__init__.py
cedar/ast.py
cedar/cli.py
cedar/errors.py
cedar/parser.py
cedar/pretty.py
cedar/tokenizer.py
cedar/typechecker.py
cedar.egg-info/PKG-INFO
cedar.egg-info/SOURCES.txt
cedar.egg-info/dependency_links.txt
cedar.egg-info/entry_points.txt
cedar.egg-info/requires.txt
cedar.egg-info/top_level.txt
cedar/languages/__init__.py
cedar/languages/cedar.py
cedar/languages/elm.py
cedar/languages/go.py
tests/__init__.py
tests/common.py
tests/test_cli.py
tests/test_codegen.py
tests/test_parser.py
tests/test_typechecker.py