Metadata-Version: 1.1
Name: cedar
Version: 0.2.10
Summary: A web service definition format and source code generator.
Home-page: https://github.com/Bogdanp/cedar
Author: Bogdan Popa
Author-email: popa.bogdanp@gmail.com
License: BSD3
Platform: UNKNOWN
Classifier: Development Status :: 3 - Alpha
Classifier: Intended Audience :: Developers
Classifier: Natural Language :: English
Classifier: License :: OSI Approved :: BSD License
Classifier: Programming Language :: Python :: 3
Classifier: Programming Language :: Python :: 3.5
